README.md
pylyrics3.py
setup.cfg
setup.py
pylyrics3.egg-info/PKG-INFO
pylyrics3.egg-info/SOURCES.txt
pylyrics3.egg-info/dependency_links.txt
pylyrics3.egg-info/requires.txt
pylyrics3.egg-info/top_level.txt