Metadata-Version: 1.1
Name: pylyrics3
Version: 1.0.6
Summary: This is a package that downloads lyrics from LyricWiki.
Home-page: https://github.com/jameswenzel/Lyric-Wiki-Scraper
Author: James Wenzel
Author-email: wenzel.james.r@gmail.com
License: Apache License, Version 2.0
Download-URL: https://github.com/jameswenzel/pylyrics3/tarball/1.0.6
Keywords: lyrics,pylyrics,lyricwiki,music
Platform: UNKNOWN
